ghget/__init__.py
ghget/gh.py
ghget/main.py
ghget-0.3.1.dist-info/LICENSE
ghget-0.3.1.dist-info/METADATA
ghget-0.3.1.dist-info/WHEEL
ghget-0.3.1.dist-info/entry_points.txt
ghget-0.3.1.dist-info/top_level.txt
ghget-0.3.1.dist-info/RECORD
