Metadata-Version: 2.1
Name: ghget
Version: 0.3.1
Summary: Download single files or folders from a github repository without cloning its entire contents.
Home-page: https://github.com/marwanhawari/ghget
Author: Marwan Hawari
Author-email: marwan.hawari@gmail.com
License: MIT
Platform: UNKNOWN
Classifier: Programming Language :: Python :: 3
Classifier: License :: OSI Approved :: MIT License
Classifier: Operating System :: OS Independent
Requires-Python: >=3.9
License-File: LICENSE
Requires-Dist: requests
Requires-Dist: requests-html
